[
  {
    "Id": "EMOTE_GENERIC_POINT_EYES",
    "Type": "emote",
    "Subtype": "emote",
    "GameAsset": null,
    "ImageId": "",
    "RMTPrice": -1,
    "GamePrice": -1,
    "IsPurchasable": false,
    "IsPublished": true,
    "IsDroppable": false,
    "Capabilities": [],
    "Qualities": {},
    "Properties": {
      "Rarity": "common",
      "IsConsumable": false,
      "RepositoryId": "1bce54d8-f2d3-491c-a7b0-c2a1cfb96765"
    },
    "Guid": "1e4d2109-42cb-46d1-9837-62b292c585a7",
    "Rarity": "common",
    "DisplayNameLocKey": "UI_EMOTE_GENERIC_POINT_EYES_NAME"
  },
  {
    "Id": "EMOTE_GENERIC_SHAKEHEAD_03",
    "Type": "emote",
    "Subtype": "emote",
    "GameAsset": null,
    "ImageId": "",
    "RMTPrice": -1,
    "GamePrice": -1,
    "IsPurchasable": false,
    "IsPublished": true,
    "IsDroppable": false,
    "Capabilities": [],
    "Qualities": {},
    "Properties": {
      "Rarity": "common",
      "IsConsumable": false,
      "RepositoryId": "afff1eef-dfd6-488d-9e88-1a7e99ad1fde"
    },
    "Guid": "41ae1755-3ec1-480a-b346-b99f365d92c6",
    "Rarity": "common",
    "DisplayNameLocKey": "UI_EMOTE_GENERIC_SHAKEHEAD_03_NAME"
  },
  {
    "Id": "EMOTE_GENERIC_KISS_01",
    "Type": "emote",
    "Subtype": "emote",
    "GameAsset": null,
    "ImageId": "",
    "RMTPrice": -1,
    "GamePrice": -1,
    "IsPurchasable": false,
    "IsPublished": true,
    "IsDroppable": false,
    "Capabilities": [],
    "Qualities": {},
    "Properties": {
      "Rarity": "common",
      "IsConsumable": false,
      "RepositoryId": "80c9794a-0702-4cf7-a401-c4b03f9a93f1",
      "OrderIndex": 100
    },
    "Guid": "0e8c04ff-cb94-439f-8e96-e7be2faf0210",
    "Rarity": "common",
    "DisplayNameLocKey": "UI_EMOTE_GENERIC_KISS_01_NAME"
  },
  {
    "Id": "EMOTE_GENERIC_SLOW_CLAP",
    "Type": "emote",
    "Subtype": "emote",
    "GameAsset": null,
    "ImageId": "",
    "RMTPrice": -1,
    "GamePrice": -1,
    "IsPurchasable": false,
    "IsPublished": true,
    "IsDroppable": false,
    "Capabilities": [],
    "Qualities": {},
    "Properties": {
      "Rarity": "common",
      "IsConsumable": false,
      "RepositoryId": "ea831558-5492-44a3-8fde-ed2ddf914e06"
    },
    "Guid": "830a43e1-5c63-4a3b-a42b-63540bcef1ad",
    "Rarity": "common",
    "DisplayNameLocKey": "UI_EMOTE_GENERIC_SLOW_CLAP_NAME"
  },
  {
    "Properties": {
      "Icon": "images/locations/LOCATION_SNUG/snug_tile.jpg",
      "Background": "images/locations/LOCATION_SNUG/snug_background.jpg",
      "LockedIcon": "images/test/elephant_tile.jpg",
      "DlcImage": "images/livetile/dlc/tile_hitman3.jpg",
      "DlcName": "GAME_STORE_METADATA_S3_GAME_TITLE",
      "IsLocked": false,
      "UpcomingContent": false,
      "UpcomingKey": "UI_MENU_LIVETILE_CONTENT_UPCOMING_HEADLINE",
      "Order": 1100,
      "LimitedLoadout": false,
      "ProgressionKey": "LOCATION_SNUG",
      "Season": 3,
      "RequiredResources": ["[assembly:/_pro/scenes/missions/snug/scene_vanilla.entity].entitytemplate"],
      "Entitlements": ["LOCATION_GOLDEN"],
      "GameMode": "Evergreen"
    },
    "Rarity": null,
    "DisplayNameLocKey": "UI_LOCATION_PARENT_SNUG_NAME",
    "Id": "LOCATION_PARENT_SNUG",
    "Type": "location",
    "Subtype": "location",
    "GameAsset": null,
    "ImageId": "",
    "RMTPrice": -1,
    "GamePrice": -1,
    "IsPurchasable": false,
    "IsPublished": true,
    "IsDroppable": false,
    "Capabilities": [],
    "Qualities": {},
    "Guid": "149a03a3-6602-4bff-8a51-2434072cf148"
  },
  {
    "Properties": {
      "ParentLocation": "LOCATION_PARENT_SNUG",
      "Icon": "images/locations/LOCATION_ELEGANT/elegant_tile.jpg",
      "Background": "images/locations/LOCATION_ELEGANT/elegant_background.jpg",
      "LockedIcon": "images/locations/LOCATION_ELEGANT/elegant_tile_unreleased.jpg",
      "DlcImage": "images/livetile/dlc/tile_hitman3.jpg",
      "DlcName": "GAME_STORE_METADATA_S3_GAME_TITLE",
      "IsLocked": false,
      "UpcomingContent": false,
      "UpcomingKey": "UI_MENU_LIVETILE_CONTENT_UPCOMING_HEADLINE",
      "Order": 1,
      "LimitedLoadout": false,
      "ProgressionKey": "LOCATION_SNUG",
      "Season": 1,
      "CreateContractId": "736066a9-b822-49b3-abaf-2e6958f2b0bc",
      "RequiredResources": ["[assembly:/_pro/scenes/missions/paris/_Scene_FashionShowHit_01.entity].entitytemplate"],
      "GameMode": "Evergreen",
      "IsHidden": true,
      "OriginalLocation": "LOCATION_PARIS",
      "Entitlements": ["H1_LEGACY_STANDARD"]
    },
    "Rarity": null,
    "DisplayNameLocKey": "UI_LOCATION_SNUG_PARIS_CRAPS_NAME",
    "Id": "LOCATION_SNUG_PARIS_CRAPS",
    "Type": "location",
    "Subtype": "sublocation",
    "GameAsset": null,
    "ImageId": "",
    "RMTPrice": -1,
    "GamePrice": -1,
    "IsPurchasable": false,
    "IsPublished": true,
    "IsDroppable": false,
    "Capabilities": [],
    "Qualities": {},
    "Guid": "042ec9ef-9966-43cd-8b50-cc632725fbe2"
  },
  {
    "Properties": {
      "ParentLocation": "LOCATION_PARENT_SNUG",
      "Background": "images/locations/LOCATION_COASTALTOWN/background.jpg",
      "Icon": "images/locations/location_coastaltown/tile.jpg",
      "LockedIcon": "images/locations/LOCATION_COASTALTOWN/tile_unreleased.jpg",
      "DlcImage": "images/livetile/dlc/tile_hitman3.jpg",
      "DlcName": "GAME_STORE_METADATA_S3_GAME_TITLE",
      "IsLocked": false,
      "GameChangers": [],
      "Order": 0,
      "ProgressionKey": "LOCATION_SNUG",
      "CreateContractId": "3984dfed-edd5-4697-a1a2-1c3a77f580f5",
      "Season": 1,
      "RequiredResources": ["[assembly:/_PRO/Scenes/Missions/CoastalTown/_scene_octopus.entity].entitytemplate"],
      "GameMode": "Evergreen",
      "IsHidden": true,
      "OriginalLocation": "LOCATION_COASTALTOWN",
      "Entitlements": ["H1_LEGACY_STANDARD"]
    },
    "Rarity": null,
    "DisplayNameLocKey": "UI_LOCATION_SNUG_COASTALTOWN_BINGO_NAME",
    "Id": "LOCATION_SNUG_COASTALTOWN_BINGO",
    "Type": "location",
    "Subtype": "sublocation",
    "GameAsset": null,
    "ImageId": "",
    "RMTPrice": -1,
    "GamePrice": -1,
    "IsPurchasable": false,
    "IsPublished": true,
    "IsDroppable": false,
    "Capabilities": [],
    "Qualities": {},
    "Guid": "8bf8b984-3f52-445e-8515-5113f80af5d4"
  },
  {
    "Properties": {
      "ParentLocation": "LOCATION_PARENT_SNUG",
      "Icon": "images/locations/LOCATION_ELEGANT/elegant_tile.jpg",
      "Background": "images/locations/LOCATION_ELEGANT/elegant_background.jpg",
      "LockedIcon": "images/locations/LOCATION_ELEGANT/elegant_tile_unreleased.jpg",
      "DlcImage": "images/livetile/dlc/tile_hitman3.jpg",
      "DlcName": "GAME_STORE_METADATA_S3_GAME_TITLE",
      "IsLocked": false,
      "UpcomingContent": false,
      "UpcomingKey": "UI_MENU_LIVETILE_CONTENT_UPCOMING_HEADLINE",
      "Order": 1,
      "LimitedLoadout": false,
      "ProgressionKey": "LOCATION_SNUG",
      "Season": 1,
      "CreateContractId": "d15b6ed0-52f8-49bf-9136-63717fd31f80",
      "RequiredResources": ["[assembly:/_pro/scenes/missions/Marrakesh/_Scene_Mission_Spider.entity].entitytemplate"],
      "GameMode": "Evergreen",
      "IsHidden": true,
      "OriginalLocation": "LOCATION_Marrakesh",
      "Entitlements": ["H1_LEGACY_STANDARD"]
    },
    "Rarity": null,
    "DisplayNameLocKey": "UI_LOCATION_SNUG_MARRAKESH_MANCALA_NAME",
    "Id": "LOCATION_SNUG_MARRAKESH_MANCALA",
    "Type": "location",
    "Subtype": "sublocation",
    "GameAsset": null,
    "ImageId": "",
    "RMTPrice": -1,
    "GamePrice": -1,
    "IsPurchasable": false,
    "IsPublished": true,
    "IsDroppable": false,
    "Capabilities": [],
    "Qualities": {},
    "Guid": "f800988f-aa0a-4990-8d6f-554630e61261"
  },
  {
    "Properties": {
      "ParentLocation": "LOCATION_PARENT_SNUG",
      "Icon": "images/locations/LOCATION_ELEGANT/elegant_tile.jpg",
      "Background": "images/locations/LOCATION_ELEGANT/elegant_background.jpg",
      "LockedIcon": "images/locations/LOCATION_ELEGANT/elegant_tile_unreleased.jpg",
      "DlcImage": "images/livetile/dlc/tile_hitman3.jpg",
      "DlcName": "GAME_STORE_METADATA_S3_GAME_TITLE",
      "IsLocked": false,
      "UpcomingContent": false,
      "UpcomingKey": "UI_MENU_LIVETILE_CONTENT_UPCOMING_HEADLINE",
      "Order": 1,
      "LimitedLoadout": false,
      "ProgressionKey": "LOCATION_SNUG",
      "Season": 1,
      "CreateContractId": "32cf79de-9fdd-45bc-864d-404a0966df73",
      "RequiredResources": ["[assembly:/_pro/scenes/missions/Bangkok/_Scene_Mission_Tiger.entity].entitytemplate"],
      "GameMode": "Evergreen",
      "IsHidden": true,
      "OriginalLocation": "LOCATION_BANGKOK",
      "Entitlements": ["H1_LEGACY_STANDARD"]
    },
    "Rarity": null,
    "DisplayNameLocKey": "UI_LOCATION_SNUG_BANGKOK_SICBO_NAME",
    "Id": "LOCATION_SNUG_BANGKOK_SICBO",
    "Type": "location",
    "Subtype": "sublocation",
    "GameAsset": null,
    "ImageId": "",
    "RMTPrice": -1,
    "GamePrice": -1,
    "IsPurchasable": false,
    "IsPublished": true,
    "IsDroppable": false,
    "Capabilities": [],
    "Qualities": {},
    "Guid": "45c4bd7c-03b5-47e7-9ec6-a76b34be93a9"
  },
  {
    "Properties": {
      "ParentLocation": "LOCATION_PARENT_SNUG",
      "Icon": "images/locations/LOCATION_ELEGANT/elegant_tile.jpg",
      "Background": "images/locations/LOCATION_ELEGANT/elegant_background.jpg",
      "LockedIcon": "images/locations/LOCATION_ELEGANT/elegant_tile_unreleased.jpg",
      "DlcImage": "images/livetile/dlc/tile_hitman3.jpg",
      "DlcName": "GAME_STORE_METADATA_S3_GAME_TITLE",
      "IsLocked": false,
      "UpcomingContent": false,
      "UpcomingKey": "UI_MENU_LIVETILE_CONTENT_UPCOMING_HEADLINE",
      "Order": 1,
      "LimitedLoadout": false,
      "ProgressionKey": "LOCATION_SNUG",
      "Season": 1,
      "CreateContractId": "efe54fab-bc14-4a2c-ae5b-dbfb509cc7a3",
      "RequiredResources": ["[assembly:/_PRO/Scenes/Missions/Colorado_2/_scene_mission_bull.entity].entitytemplate"],
      "GameMode": "Evergreen",
      "IsHidden": true,
      "OriginalLocation": "LOCATION_COLORADO",
      "Entitlements": ["H1_LEGACY_STANDARD"]
    },
    "Rarity": null,
    "DisplayNameLocKey": "UI_LOCATION_SNUG_COLORADO_SPADES_NAME",
    "Id": "LOCATION_SNUG_COLORADO_SPADES",
    "Type": "location",
    "Subtype": "sublocation",
    "GameAsset": null,
    "ImageId": "",
    "RMTPrice": -1,
    "GamePrice": -1,
    "IsPurchasable": false,
    "IsPublished": true,
    "IsDroppable": false,
    "Capabilities": [],
    "Qualities": {},
    "Guid": "a383c8c3-6c65-42e7-a725-df7701c0c2ec"
  },
  {
    "Properties": {
      "ParentLocation": "LOCATION_PARENT_SNUG",
      "Icon": "images/locations/LOCATION_HOKKAIDO/hokkaido_tile.jpg",
      "Background": "images/locations/LOCATION_HOKKAIDO/hokkaido_background.jpg",
      "LockedIcon": "images/locations/LOCATION_HOKKAIDO/hokkaido_tile_unreleased.jpg",
      "DlcImage": "images/livetile/dlc/tile_hitman3.jpg",
      "DlcName": "GAME_STORE_METADATA_S3_GAME_TITLE",
      "IsLocked": false,
      "UpcomingContent": false,
      "UpcomingKey": "UI_MENU_LIVETILE_CONTENT_UPCOMING_HEADLINE",
      "Order": 1,
      "LimitedLoadout": false,
      "ProgressionKey": "LOCATION_SNUG",
      "Season": 1,
      "CreateContractId": "968179e7-4e5f-4c51-83ed-6e68ea0c72ea",
      "RequiredResources": [
        "[assembly:/_pro/scenes/missions/hokkaido/_Scene_Mission_SnowCrane.entity].entitytemplate"
      ],
      "GameMode": "Evergreen",
      "IsHidden": true,
      "OriginalLocation": "LOCATION_HOKKAIDO",
      "Entitlements": [
        "H1_LEGACY_STANDARD"
      ]
    },
    "Rarity": null,
    "DisplayNameLocKey": "UI_LOCATION_SNUG_HOKKAIDO_SHOGI_NAME",
    "Id": "LOCATION_SNUG_HOKKAIDO_SHOGI",
    "Type": "location",
    "Subtype": "sublocation",
    "GameAsset": null,
    "ImageId": "",
    "RMTPrice": -1,
    "GamePrice": -1,
    "IsPurchasable": false,
    "IsPublished": true,
    "IsDroppable": false,
    "Capabilities": [],
    "Qualities": {},
    "Guid": "31656510-9d2f-4061-aa59-de68aece54b8"
  },
  {
    "Properties": {
      "ParentLocation": "LOCATION_PARENT_SNUG",
      "Icon": "images/locations/LOCATION_FLAMINGO/flamingo_tile.jpg",
      "Background": "images/locations/LOCATION_FLAMINGO/flamingo_background.jpg",
      "LockedIcon": "images/locations/LOCATION_FLAMINGO/flamingo_tile_unreleased.jpg",
      "DlcImage": "images/livetile/dlc/tile_hitman3.jpg",
      "DlcName": "GAME_STORE_METADATA_S3_GAME_TITLE",
      "IsLocked": false,
      "UpcomingContent": false,
      "UpcomingKey": "UI_MENU_LIVETILE_CONTENT_UPCOMING_HEADLINE",
      "Order": 1,
      "LimitedLoadout": false,
      "ProgressionKey": "LOCATION_SNUG",
      "Season": 2,
      "CreateContractId": "1e680843-f484-4579-9032-a5ac349f85cd",
      "RequiredResources": ["[assembly:/_pro/scenes/missions/miami/scene_flamingo.entity].entitytemplate"],
      "GameMode": "Evergreen",
      "IsHidden": true,
      "OriginalLocation": "LOCATION_MIAMI",
      "Entitlements": ["H2_LEGACY_STANDARD"]
    },
    "Rarity": null,
    "DisplayNameLocKey": "UI_LOCATION_SNUG_MIAMI_PINOCHLE_NAME",
    "Id": "LOCATION_SNUG_MIAMI_PINOCHLE",
    "Type": "location",
    "Subtype": "sublocation",
    "GameAsset": null,
    "ImageId": "",
    "RMTPrice": -1,
    "GamePrice": -1,
    "IsPurchasable": false,
    "IsPublished": true,
    "IsDroppable": false,
    "Capabilities": [],
    "Qualities": {},
    "Guid": "17618835-0514-4af3-99f4-443006cbeec4"
  },
  {
    "Properties": {
      "ParentLocation": "LOCATION_PARENT_SNUG",
      "Icon": "images/locations/LOCATION_COLOMBIA/tile.jpg",
      "Background": "images/locations/LOCATION_COLOMBIA/background.jpg",
      "LockedIcon": "images/locations/LOCATION_COLOMBIA/tile_unreleased.jpg",
      "DlcImage": "images/livetile/dlc/tile_hitman3.jpg",
      "DlcName": "GAME_STORE_METADATA_S3_GAME_TITLE",
      "IsLocked": false,
      "UpcomingContent": false,
      "UpcomingKey": "UI_MENU_LIVETILE_CONTENT_UPCOMING_HEADLINE",
      "Order": 1,
      "LimitedLoadout": false,
      "ProgressionKey": "LOCATION_SNUG",
      "Season": 2,
      "CreateContractId": "756ee070-5810-4443-8864-2f96c64f7c2a",
      "RequiredResources": [
        "[assembly:/_pro/scenes/missions/colombia/scene_hippo.entity].entitytemplate"
      ],
      "GameMode": "Evergreen",
      "IsHidden": true,
      "OriginalLocation": "LOCATION_COLOMBIA_HIPPO",
      "Entitlements": [
        "H1_LEGACY_STANDARD"
      ]
    },
    "Rarity": null,
    "DisplayNameLocKey": "UI_LOCATION_SNUG_COLOMBIA_HIPPO_TROMPO_NAME",
    "Id": "LOCATION_SNUG_COLOMBIA_HIPPO_TROMPO",
    "Type": "location",
    "Subtype": "sublocation",
    "GameAsset": null,
    "ImageId": "",
    "RMTPrice": -1,
    "GamePrice": -1,
    "IsPurchasable": false,
    "IsPublished": true,
    "IsDroppable": false,
    "Capabilities": [],
    "Qualities": {},
    "Guid": "8502c3ea-6752-491c-ab5f-ff8cac185c15"
  },
  {
    "Properties": {
      "ParentLocation": "LOCATION_PARENT_SNUG",
      "Icon": "images/locations/LOCATION_MUMBAI/tile.jpg",
      "Background": "images/locations/LOCATION_MUMBAI/background.jpg",
      "LockedIcon": "images/locations/LOCATION_MUMBAI/tile_unreleased.jpg",
      "DlcImage": "images/livetile/dlc/tile_hitman3.jpg",
      "DlcName": "GAME_STORE_METADATA_S3_GAME_TITLE",
      "IsLocked": false,
      "UpcomingContent": false,
      "UpcomingKey": "UI_MENU_LIVETILE_CONTENT_UPCOMING_HEADLINE",
      "Order": 1,
      "LimitedLoadout": false,
      "ProgressionKey": "LOCATION_SNUG",
      "CreateContractId": "e00ea75e-2596-4a78-b0fd-12e583db5bde",
      "Season": 2,
      "RequiredResources": ["[assembly:/_PRO/Scenes/Missions/Mumbai/scene_mongoose.entity].entitytemplate"],
      "GameMode": "Evergreen",
      "IsHidden": true,
      "OriginalLocation": "LOCATION_MUMBAI",
      "Entitlements": ["H2_LEGACY_STANDARD"]
    },
    "Rarity": null,
    "DisplayNameLocKey": "UI_LOCATION_SNUG_MUMBAI_LUDO_NAME",
    "Id": "LOCATION_SNUG_MUMBAI_LUDO",
    "Type": "location",
    "Subtype": "sublocation",
    "GameAsset": null,
    "ImageId": "",
    "RMTPrice": -1,
    "GamePrice": -1,
    "IsPurchasable": false,
    "IsPublished": true,
    "IsDroppable": false,
    "Capabilities": [],
    "Qualities": {},
    "Guid": "88d09052-1dab-4983-9812-74aa921e4261"
  },
  {
    "Properties": {
      "ParentLocation": "LOCATION_PARENT_SNUG",
      "Icon": "images/locations/LOCATION_NORTHAMERICA/northamerica_tile.jpg",
      "Background": "images/locations/LOCATION_NORTHAMERICA/northamerica_background.jpg",
      "LockedIcon": "images/locations/LOCATION_NORTHAMERICA/northamerica_tile_unreleased.jpg",
      "DlcImage": "images/livetile/dlc/tile_hitman3.jpg",
      "DlcName": "GAME_STORE_METADATA_S3_GAME_TITLE",
      "IsLocked": false,
      "UpcomingContent": false,
      "UpcomingKey": "UI_MENU_LIVETILE_CONTENT_UPCOMING_HEADLINE",
      "Order": 1,
      "LimitedLoadout": false,
      "ProgressionKey": "LOCATION_SNUG",
      "Season": 2,
      "CreateContractId": "8b7c852b-3fd2-4bfa-a4b8-d8c166196050",
      "RequiredResources": ["[assembly:/_pro/scenes/missions/skunk/scene_skunk.entity].entitytemplate"],
      "GameMode": "Evergreen",
      "IsHidden": true,
      "OriginalLocation": "LOCATION_NORTHAMERICA",
      "Entitlements": ["H2_LEGACY_STANDARD"]
    },
    "Rarity": null,
    "DisplayNameLocKey": "UI_LOCATION_SNUG_NORTHAMERICA_SOLITAIRE_NAME",
    "Id": "LOCATION_SNUG_NORTHAMERICA_SOLITAIRE",
    "Type": "location",
    "Subtype": "sublocation",
    "GameAsset": null,
    "ImageId": "",
    "RMTPrice": -1,
    "GamePrice": -1,
    "IsPurchasable": false,
    "IsPublished": true,
    "IsDroppable": false,
    "Capabilities": [],
    "Qualities": {},
    "Guid": "3cbf362d-0415-4d6a-9eda-dda863133c8b"
  },
  {
    "Properties": {
      "ParentLocation": "LOCATION_PARENT_SNUG",
      "Icon": "images/locations/LOCATION_NORTHSEA/northsea_tile.jpg",
      "Background": "images/locations/LOCATION_NORTHSEA/northsea_background.jpg",
      "LockedIcon": "images/locations/LOCATION_NORTHSEA/northsea_tile_unreleased.jpg",
      "DlcImage": "images/livetile/dlc/tile_hitman3.jpg",
      "DlcName": "GAME_STORE_METADATA_S3_GAME_TITLE",
      "IsLocked": false,
      "UpcomingContent": false,
      "UpcomingKey": "UI_MENU_LIVETILE_CONTENT_UPCOMING_HEADLINE",
      "Order": 1,
      "LimitedLoadout": false,
      "ProgressionKey": "LOCATION_SNUG",
      "Season": 2,
      "CreateContractId": "79a904b7-10f0-45af-9c28-5af76cec8ec1",
      "RequiredResources": [
        "[assembly:/_pro/scenes/missions/theark/scene_magpie.entity].entitytemplate"
      ],
      "GameMode": "Evergreen",
      "IsHidden": true,
      "OriginalLocation": "LOCATION_NORTHSEA",
      "Entitlements": [
        "H2_LEGACY_STANDARD"
      ]
    },
    "Rarity": null,
    "DisplayNameLocKey": "UI_LOCATION_SNUG_NORTHSEA_WHIST_NAME",
    "Id": "LOCATION_SNUG_NORTHSEA_WHIST",
    "Type": "location",
    "Subtype": "sublocation",
    "GameAsset": null,
    "ImageId": "",
    "RMTPrice": -1,
    "GamePrice": -1,
    "IsPurchasable": false,
    "IsPublished": true,
    "IsDroppable": false,
    "Capabilities": [],
    "Qualities": {},
    "Guid": "4e58b029-4b09-4b00-aec7-e4ffb432bf00"
  },
  {
    "Properties": {
      "ParentLocation": "LOCATION_PARENT_SNUG",
      "Icon": "images/locations/LOCATION_ELEGANT/elegant_tile.jpg",
      "Background": "images/locations/LOCATION_ELEGANT/elegant_background.jpg",
      "LockedIcon": "images/locations/LOCATION_ELEGANT/elegant_tile_unreleased.jpg",
      "DlcImage": "images/livetile/dlc/tile_hitman3.jpg",
      "DlcName": "GAME_STORE_METADATA_S3_GAME_TITLE",
      "IsLocked": false,
      "UpcomingContent": false,
      "UpcomingKey": "UI_MENU_LIVETILE_CONTENT_UPCOMING_HEADLINE",
      "Order": 1,
      "LimitedLoadout": false,
      "ProgressionKey": "LOCATION_SNUG",
      "Season": 2,
      "CreateContractId": "19451588-a369-44df-bbf1-887c41f87501",
      "RequiredResources": ["[assembly:/_pro/scenes/missions/greedy/mission_raccoon/scene_raccoon_basic.entity].entitytemplate"],
      "GameMode": "Evergreen",
      "IsHidden": true,
      "OriginalLocation": "LOCATION_RACCOON_GREEDY",
      "Entitlements": ["LOCATION_GREEDY"]
    },
    "Rarity": null,
    "DisplayNameLocKey": "UI_LOCATION_SNUG_GREEDY_BLACKJACK_NAME",
    "Id": "LOCATION_SNUG_GREEDY_BLACKJACK",
    "Type": "location",
    "Subtype": "sublocation",
    "GameAsset": null,
    "ImageId": "",
    "RMTPrice": -1,
    "GamePrice": -1,
    "IsPurchasable": false,
    "IsPublished": true,
    "IsDroppable": false,
    "Capabilities": [],
    "Qualities": {},
    "Guid": "08fb54f9-6373-4ad9-a3fa-60e51703bb48"
  },
  {
    "Properties": {
      "ParentLocation": "LOCATION_PARENT_SNUG",
      "Icon": "images/locations/LOCATION_ELEGANT/elegant_tile.jpg",
      "Background": "images/locations/LOCATION_ELEGANT/elegant_background.jpg",
      "LockedIcon": "images/locations/LOCATION_ELEGANT/elegant_tile_unreleased.jpg",
      "DlcImage": "images/livetile/dlc/tile_hitman3.jpg",
      "DlcName": "GAME_STORE_METADATA_S3_GAME_TITLE",
      "IsLocked": false,
      "UpcomingContent": false,
      "UpcomingKey": "UI_MENU_LIVETILE_CONTENT_UPCOMING_HEADLINE",
      "Order": 1,
      "LimitedLoadout": false,
      "ProgressionKey": "LOCATION_SNUG",
      "Season": 2,
      "CreateContractId": "13b96942-5549-4e95-92be-2111fe33f3db",
      "RequiredResources": ["[assembly:/_pro/scenes/missions/opulent/mission_stingray/scene_stingray_basic.entity].entitytemplate"],
      "GameMode": "Evergreen",
      "IsHidden": true,
      "OriginalLocation": "LOCATION_OPULENT",
      "Entitlements": ["H2_LEGACY_STANDARD"]
    },
    "Rarity": null,
    "DisplayNameLocKey": "UI_LOCATION_SNUG_OPULENT_HILO_NAME",
    "Id": "LOCATION_SNUG_OPULENT_HILO",
    "Type": "location",
    "Subtype": "sublocation",
    "GameAsset": null,
    "ImageId": "",
    "RMTPrice": -1,
    "GamePrice": -1,
    "IsPurchasable": false,
    "IsPublished": true,
    "IsDroppable": false,
    "Capabilities": [],
    "Qualities": {},
    "Guid": "c28b0897-bb58-4961-8683-08d02dad90e7"
  },
  {
    "Properties": {
      "ParentLocation": "LOCATION_PARENT_SNUG",
      "Icon": "images/locations/LOCATION_GOLDEN/golden_tile.jpg",
      "Background": "images/locations/LOCATION_GOLDEN/golden_background.jpg",
      "LockedIcon": "images/locations/LOCATION_GOLDEN/golden_tile_unreleased.jpg",
      "DlcImage": "images/livetile/dlc/tile_hitman3.jpg",
      "DlcName": "GAME_STORE_METADATA_S3_GAME_TITLE",
      "IsLocked": false,
      "UpcomingContent": false,
      "UpcomingKey": "UI_MENU_LIVETILE_CONTENT_UPCOMING_HEADLINE",
      "Order": 1,
      "LimitedLoadout": false,
      "ProgressionKey": "LOCATION_SNUG",
      "Season": 3,
      "CreateContractId": "3fcce3d8-fc09-436c-bd12-d3298f459538",
      "RequiredResources": ["[assembly:/_pro/scenes/missions/golden/mission_gecko/scene_gecko_basic.entity].entitytemplate"],
      "GameMode": "Evergreen",
      "IsHidden": true,
      "OriginalLocation": "LOCATION_GOLDEN_GECKO",
      "Entitlements": ["LOCATION_GOLDEN"]
    },
    "Rarity": null,
    "DisplayNameLocKey": "UI_LOCATION_SNUG_GOLDEN_GECKO_CHESS_NAME",
    "Id": "LOCATION_SNUG_GOLDEN_GECKO_CHESS",
    "Type": "location",
    "Subtype": "sublocation",
    "GameAsset": null,
    "ImageId": "",
    "RMTPrice": -1,
    "GamePrice": -1,
    "IsPurchasable": false,
    "IsPublished": true,
    "IsDroppable": false,
    "Capabilities": [],
    "Qualities": {},
    "Guid": "4c1f36ce-8efe-4669-9d4e-02c96ba15c1f"
  },
  {
    "Properties": {
      "ParentLocation": "LOCATION_PARENT_SNUG",
      "Icon": "images/locations/LOCATION_ANCESTRAL/ancestral_tile.jpg",
      "Background": "images/locations/LOCATION_ANCESTRAL/ancestral_background.jpg",
      "LockedIcon": "images/locations/LOCATION_ANCESTRAL/ancestral_tile_unreleased.jpg",
      "DlcImage": "images/livetile/dlc/tile_hitman3.jpg",
      "DlcName": "GAME_STORE_METADATA_S3_GAME_TITLE",
      "IsLocked": false,
      "UpcomingContent": false,
      "UpcomingKey": "UI_MENU_LIVETILE_CONTENT_UPCOMING_HEADLINE",
      "Order": 1,
      "LimitedLoadout": false,
      "ProgressionKey": "LOCATION_SNUG",
      "Season": 3,
      "CreateContractId": "a4affaf9-ce38-42d1-8e1c-b199d7bdf4d5",
      "RequiredResources": ["[assembly:/_pro/scenes/missions/Ancestral/scene_bulldog.entity].entitytemplate"],
      "GameMode": "Evergreen",
      "IsHidden": true,
      "OriginalLocation": "LOCATION_ANCESTRAL_BULLDOG",
      "Entitlements": ["LOCATION_ANCESTRAL"]
    },
    "Rarity": null,
    "DisplayNameLocKey": "UI_LOCATION_SNUG_ANCESTRAL_BULLDOG_BRIDGE_NAME",
    "Id": "LOCATION_SNUG_ANCESTRAL_BULLDOG_BRIDGE",
    "Type": "location",
    "Subtype": "sublocation",
    "GameAsset": null,
    "ImageId": "",
    "RMTPrice": -1,
    "GamePrice": -1,
    "IsPurchasable": false,
    "IsPublished": true,
    "IsDroppable": false,
    "Capabilities": [],
    "Qualities": {},
    "Guid": "c6db39d7-dd5c-4281-830a-56cf4a505216"
  },
  {
    "Properties": {
      "ParentLocation": "LOCATION_PARENT_SNUG",
      "Icon": "images/locations/LOCATION_EDGY/edgy_tile.jpg",
      "Background": "images/locations/LOCATION_EDGY/edgy_background.jpg",
      "LockedIcon": "images/locations/LOCATION_EDGY/edgy_tile_unreleased.jpg",
      "DlcImage": "images/livetile/dlc/tile_hitman3.jpg",
      "DlcName": "GAME_STORE_METADATA_S3_GAME_TITLE",
      "IsLocked": false,
      "UpcomingContent": false,
      "UpcomingKey": "UI_MENU_LIVETILE_CONTENT_UPCOMING_HEADLINE",
      "Order": 1,
      "LimitedLoadout": false,
      "ProgressionKey": "LOCATION_SNUG",
      "Season": 3,
      "CreateContractId": "daf81d6c-70ed-4060-bbbf-8722027fa868",
      "RequiredResources": ["[assembly:/_PRO/Scenes/Missions/edgy/mission_fox/scene_fox_basic.entity].entitytemplate"],
      "GameMode": "Evergreen",
      "IsHidden": true,
      "OriginalLocation": "LOCATION_EDGY_FOX",
      "Entitlements": ["LOCATION_EDGY"]
    },
    "Rarity": null,
    "DisplayNameLocKey": "UI_LOCATION_SNUG_EDGY_FOX_MEYER_NAME",
    "Id": "LOCATION_SNUG_EDGY_FOX_MEYER",
    "Type": "location",
    "Subtype": "sublocation",
    "GameAsset": null,
    "ImageId": "",
    "RMTPrice": -1,
    "GamePrice": -1,
    "IsPurchasable": false,
    "IsPublished": true,
    "IsDroppable": false,
    "Capabilities": [],
    "Qualities": {},
    "Guid": "fe8eb67c-7a7e-4d39-b755-05ed3811f544"
  },
  {
    "Properties": {
      "ParentLocation": "LOCATION_PARENT_SNUG",
      "Icon": "images/locations/LOCATION_WET/wet_tile.jpg",
      "Background": "images/locations/LOCATION_WET/wet_background.jpg",
      "LockedIcon": "images/locations/LOCATION_WET/wet_tile_unreleased.jpg",
      "DlcImage": "images/livetile/dlc/tile_hitman3.jpg",
      "DlcName": "GAME_STORE_METADATA_S3_GAME_TITLE",
      "IsLocked": false,
      "UpcomingContent": false,
      "UpcomingKey": "UI_MENU_LIVETILE_CONTENT_UPCOMING_HEADLINE",
      "Order": 1,
      "LimitedLoadout": false,
      "ProgressionKey": "LOCATION_SNUG",
      "Season": 3,
      "CreateContractId": "451bdccf-fa3a-4aba-8b81-9c7f19c7490a",
      "RequiredResources": ["[assembly:/_PRO/Scenes/Missions/wet/scene_rat_basic.entity].entitytemplate"],
      "GameMode": "Evergreen",
      "IsHidden": true,
      "OriginalLocation": "LOCATION_WET_RAT",
      "Entitlements": ["LOCATION_WET"]
    },
    "Rarity": null,
    "DisplayNameLocKey": "UI_LOCATION_SNUG_WET_RAT_MAHJONG_NAME",
    "Id": "LOCATION_SNUG_WET_RAT_MAHJONG",
    "Type": "location",
    "Subtype": "sublocation",
    "GameAsset": null,
    "ImageId": "",
    "RMTPrice": -1,
    "GamePrice": -1,
    "IsPurchasable": false,
    "IsPublished": true,
    "IsDroppable": false,
    "Capabilities": [],
    "Qualities": {},
    "Guid": "2f91200b-5dc4-4f85-9c1a-275cebe69102"
  },
  {
    "Properties": {
      "ParentLocation": "LOCATION_PARENT_SNUG",
      "Icon": "images/locations/LOCATION_ELEGANT/elegant_tile.jpg",
      "Background": "images/locations/LOCATION_ELEGANT/elegant_background.jpg",
      "LockedIcon": "images/locations/LOCATION_ELEGANT/elegant_tile_unreleased.jpg",
      "DlcImage": "images/livetile/dlc/tile_hitman3.jpg",
      "DlcName": "GAME_STORE_METADATA_S3_GAME_TITLE",
      "IsLocked": false,
      "UpcomingContent": false,
      "UpcomingKey": "UI_MENU_LIVETILE_CONTENT_UPCOMING_HEADLINE",
      "Order": 1,
      "LimitedLoadout": false,
      "ProgressionKey": "LOCATION_SNUG",
      "Season": 3,
      "CreateContractId": "ac8147eb-9a56-4768-bf7c-db0523637093",
      "RequiredResources": [
        "[assembly:/_pro/scenes/missions/elegant/scene_llama.entity].entitytemplate"
      ],
      "GameMode": "Evergreen",
      "IsHidden": true,
      "OriginalLocation": "LOCATION_ELEGANT_LLAMA",
      "Entitlements": [
        "LOCATION_ELEGANT"
      ]
    },
    "Rarity": null,
    "DisplayNameLocKey": "UI_LOCATION_SNUG_ELEGANT_LLAMA_SAPO_NAME",
    "Id": "LOCATION_SNUG_ELEGANT_LLAMA_SAPO",
    "Type": "location",
    "Subtype": "sublocation",
    "GameAsset": null,
    "ImageId": "",
    "RMTPrice": -1,
    "GamePrice": -1,
    "IsPurchasable": false,
    "IsPublished": true,
    "IsDroppable": false,
    "Capabilities": [],
    "Qualities": {},
    "Guid": "683623c7-dde4-4a2c-a60f-c2d01e60ee30"
  },
  {
    "Properties": {
      "ParentLocation": "LOCATION_PARENT_SNUG",
      "Icon": "images/locations/LOCATION_ROCKY/rocky_tile.jpg",
      "Background": "images/locations/LOCATION_ROCKY/rocky_background.jpg",
      "LockedIcon": "images/locations/LOCATION_ROCKY/rocky_tile_unreleased.jpg",
      "DlcImage": "images/livetile/dlc/tile_hitman3.jpg",
      "DlcName": "GAME_STORE_METADATA_S3_GAME_TITLE",
      "IsLocked": false,
      "UpcomingContent": false,
      "UpcomingKey": "UI_MENU_LIVETILE_CONTENT_UPCOMING_HEADLINE",
      "Order": 1,
      "LimitedLoadout": false,
      "ProgressionKey": "LOCATION_SNUG",
      "Season": 3,
      "CreateContractId": "5547c56a-cc5f-4f91-aa28-cfb816c06b3e",
      "RequiredResources": ["[assembly:/_pro/scenes/missions/Rocky/scene_dugong.entity].entitytemplate"],
      "GameMode": "Evergreen",
      "IsHidden": true,
      "OriginalLocation": "LOCATION_ROCKY_DUGONG",
      "Entitlements": ["LOCATION_ROCKY"]
    },
    "Rarity": null,
    "DisplayNameLocKey": "UI_LOCATION_SNUG_ROCKY_DUGONG_POKER_NAME",
    "Id": "LOCATION_SNUG_ROCKY_DUGONG_POKER",
    "Type": "location",
    "Subtype": "sublocation",
    "GameAsset": null,
    "ImageId": "",
    "RMTPrice": -1,
    "GamePrice": -1,
    "IsPurchasable": false,
    "IsPublished": true,
    "IsDroppable": false,
    "Capabilities": [],
    "Qualities": {},
    "Guid": "7bc2d91f-63d8-4a13-bab5-8d5a407ba491"
  },
  {
    "Properties": {
      "ParentLocation": "LOCATION_PARENT_SNUG",
      "Icon": "images/locations/LOCATION_SNUG/snug_tile.jpg",
      "Background": "images/locations/LOCATION_SNUG/snug_background.jpg",
      "LockedIcon": "images/test/elephant_tile.jpg",
      "DlcImage": "images/livetile/dlc/tile_hitman3.jpg",
      "DlcName": "GAME_STORE_METADATA_S3_GAME_TITLE",
      "IsLocked": false,
      "UpcomingContent": false,
      "UpcomingKey": "UI_MENU_LIVETILE_CONTENT_UPCOMING_HEADLINE",
      "Order": 1,
      "LimitedLoadout": false,
      "ProgressionKey": "LOCATION_SNUG",
      "Season": 3,
      "RequiredResources": ["[assembly:/_pro/scenes/missions/snug/scene_vanilla.entity].entitytemplate"],
      "GameMode": "Evergreen",
      "Entitlements": ["LOCATION_GOLDEN"]
    },
    "Rarity": null,
    "DisplayNameLocKey": "UI_LOCATION_SNUG_NAME",
    "Id": "LOCATION_SNUG",
    "Type": "location",
    "Subtype": "sublocation",
    "GameAsset": null,
    "ImageId": "",
    "RMTPrice": -1,
    "GamePrice": -1,
    "IsPurchasable": false,
    "IsPublished": true,
    "IsDroppable": false,
    "Capabilities": [],
    "Qualities": {},
    "Guid": "935a2416-93d8-4d59-b86c-b298978edbe8"
  }
]